{
    "name": "Preference",
    "fields": [
        {
            "fieldName": "wechat",
            "fieldType": "String",
            "fieldValidateRules": [
                "required"
            ]
        },
        {
            "fieldName": "address",
            "fieldType": "String"
        },
        {
            "fieldName": "imageUrl",
            "fieldType": "String"
        },
        {
            "fieldName": "lang",
            "fieldType": "String"
        },
        {
            "fieldName": "createdDate",
            "fieldType": "Long",
            "fieldValidateRules": [
                "required"
            ]
        },
        {
            "fieldName": "modifiedDate",
            "fieldType": "Long"
        }
    ],
    "relationships": [],
    "changelogDate": "20190124080847",
    "entityTableName": "preference",
    "dto": "no",
    "pagination": "no",
    "service": "no",
    "jpaMetamodelFiltering": false,
    "fluentMethods": true,
    "clientRootFolder": "",
    "applications": "*"
}